LICENSE
README.md
setup.py
setuptools_zig_build.py
setuptools_zig_build.egg-info/PKG-INFO
setuptools_zig_build.egg-info/SOURCES.txt
setuptools_zig_build.egg-info/dependency_links.txt
setuptools_zig_build.egg-info/entry_points.txt
setuptools_zig_build.egg-info/top_level.txt